odoo/addons/base_time_parameter/README.rst
odoo/addons/base_time_parameter/__init__.py
odoo/addons/base_time_parameter/__manifest__.py
odoo/addons/base_time_parameter/i18n/base_time_dependent_parameter.pot
odoo/addons/base_time_parameter/i18n/base_time_parameter.pot
odoo/addons/base_time_parameter/i18n/pt.po
odoo/addons/base_time_parameter/models/__init__.py
odoo/addons/base_time_parameter/models/base.py
odoo/addons/base_time_parameter/models/base_time_parameter.py
odoo/addons/base_time_parameter/models/base_time_parameter_version.py
odoo/addons/base_time_parameter/readme/CONFIGURE.rst
odoo/addons/base_time_parameter/readme/CONTRIBUTORS.rst
odoo/addons/base_time_parameter/readme/DESCRIPTION.rst
odoo/addons/base_time_parameter/readme/USAGE.rst
odoo/addons/base_time_parameter/security/ir.model.access.csv
odoo/addons/base_time_parameter/security/security.xml
odoo/addons/base_time_parameter/static/icon.png
odoo/addons/base_time_parameter/static/description/icon.png
odoo/addons/base_time_parameter/static/description/index.html
odoo/addons/base_time_parameter/tests/__init__.py
odoo/addons/base_time_parameter/tests/test_time_parameter.py
odoo/addons/base_time_parameter/views/base_time_parameter_version_views.xml
odoo/addons/base_time_parameter/views/base_time_parameter_views.xml
odoo_addon_base_time_parameter-15.0.1.0.0.2.dist-info/METADATA
odoo_addon_base_time_parameter-15.0.1.0.0.2.dist-info/WHEEL
odoo_addon_base_time_parameter-15.0.1.0.0.2.dist-info/top_level.txt
odoo_addon_base_time_parameter-15.0.1.0.0.2.dist-info/RECORD
